labw_utils/__init__.py
labw_utils/__main__.py
labw_utils/typing_importer.py
labw_utils/bioutils/__init__.py
labw_utils/bioutils/__main__.py
labw_utils/bioutils/accession_matcher.py
labw_utils/bioutils/comm_frontend_opts.py
labw_utils/bioutils/_main/__init__.py
labw_utils/bioutils/_main/describe_fasta_by_binning.py
labw_utils/bioutils/_main/describe_fastq.py
labw_utils/bioutils/_main/describe_gtf.py
labw_utils/bioutils/_main/describe_gtf_by_binning.py
labw_utils/bioutils/_main/filter_gtf_by_attribute.py
labw_utils/bioutils/_main/generate_fake_fasta.py
labw_utils/bioutils/_main/get_exonic_depth.py
labw_utils/bioutils/_main/normalize_gtf.py
labw_utils/bioutils/_main/sample_transcript.py
labw_utils/bioutils/_main/split_fasta.py
labw_utils/bioutils/_main/transcribe.py
labw_utils/bioutils/algorithm/__init__.py
labw_utils/bioutils/algorithm/alignment.py
labw_utils/bioutils/algorithm/cigar_ops.py
labw_utils/bioutils/algorithm/sequence.py
labw_utils/bioutils/algorithm/utils.py
labw_utils/bioutils/datastructure/__init__.py
labw_utils/bioutils/datastructure/fai_view.py
labw_utils/bioutils/datastructure/fasta_view.py
labw_utils/bioutils/datastructure/fastq_view.py
labw_utils/bioutils/datastructure/feature_view.py
labw_utils/bioutils/datastructure/gene_tree.py
labw_utils/bioutils/datastructure/gene_tree_helper.py
labw_utils/bioutils/datastructure/quantification_optimized_feature_index.py
labw_utils/bioutils/datastructure/region_indexer.py
labw_utils/bioutils/datastructure/transposon.py
labw_utils/bioutils/datastructure/gene_view_v0_1_x/__init__.py
labw_utils/bioutils/datastructure/gene_view_v0_1_x/_determine_filetype.py
labw_utils/bioutils/datastructure/gene_view_v0_1_x/_gv_errors.py
labw_utils/bioutils/datastructure/gene_view_v0_1_x/_gv_feature_proxy_mutator.py
labw_utils/bioutils/datastructure/gene_view_v0_1_x/gene_view.py
labw_utils/bioutils/datastructure/gene_view_v0_1_x/gv_feature_proxy.py
labw_utils/bioutils/datastructure/gene_view_v0_1_x/gv_helper.py
labw_utils-1.0.4.dist-info/Copying.md
labw_utils-1.0.4.dist-info/License.md
labw_utils-1.0.4.dist-info/METADATA
labw_utils-1.0.4.dist-info/WHEEL
labw_utils-1.0.4.dist-info/top_level.txt
labw_utils-1.0.4.dist-info/RECORD
